jphtools/__init__.py
jphtools/__main__.py
jphtools/notebooks.py
jphtools-0.2.1.dist-info/METADATA
jphtools-0.2.1.dist-info/WHEEL
jphtools-0.2.1.dist-info/entry_points.txt
jphtools-0.2.1.dist-info/RECORD
