Metadata-Version: 2.4
Name: jphtools
Version: 0.2.1
Summary: Add your description here
Author-email: JP Hwang <me@jphwang.com>
License: MIT
Requires-Python: >=3.10
Requires-Dist: click>=8.2.1
Requires-Dist: jupyter>=1.1.1
